pitayaserver/__init__.py
pitayaserver/c_interop.py
pitayaserver/pitayaserver.py
pitayaserver/remote.py
pitayaserver/route.py
pitayaserver/gen/__init__.py
pitayaserver/gen/bind_pb2.py
pitayaserver/gen/cluster_pb2.py
pitayaserver/gen/doc_pb2.py
pitayaserver/gen/docmsg_pb2.py
pitayaserver/gen/error_pb2.py
pitayaserver/gen/kick_pb2.py
pitayaserver/gen/msg_pb2.py
pitayaserver/gen/pitaya_pb2.py
pitayaserver/gen/protodescriptor_pb2.py
pitayaserver/gen/push_pb2.py
pitayaserver/gen/request_pb2.py
pitayaserver/gen/response_pb2.py
pitayaserver/gen/session_pb2.py
pitayaserver-0.2.1.dist-info/METADATA
pitayaserver-0.2.1.dist-info/WHEEL
pitayaserver-0.2.1.dist-info/top_level.txt
pitayaserver-0.2.1.dist-info/RECORD
